quantsight/__init__.py
quantsight/agent.py
quantsight/client.py
quantsight-0.1.11.dist-info/LICENSE
quantsight-0.1.11.dist-info/METADATA
quantsight-0.1.11.dist-info/WHEEL
quantsight-0.1.11.dist-info/top_level.txt
quantsight-0.1.11.dist-info/RECORD
