Metadata-Version: 2.1
Name: quantsight
Version: 0.1.11
Requires-Python: >=3.6
License-File: LICENSE
Requires-Dist: pandas
Requires-Dist: langchain
Requires-Dist: data-cache
Requires-Dist: openai
Requires-Dist: tabulate
